{
  "version-0.55-docs": {
    "The Basics": [
      "version-0.55-getting-started",
      "version-0.55-tutorial",
      "version-0.55-props",
      "version-0.55-state",
      "version-0.55-style",
      "version-0.55-height-and-width",
      "version-0.55-flexbox",
      "version-0.55-handling-text-input",
      "version-0.55-handling-touches",
      "version-0.55-using-a-scrollview",
      "version-0.55-using-a-listview",
      "version-0.55-network",
      "version-0.55-more-resources"
    ],
    "Guides": [
      "version-0.55-components-and-apis",
      "version-0.55-platform-specific-code",
      "version-0.55-navigation",
      "version-0.55-images",
      "version-0.55-animations",
      "version-0.55-accessibility",
      "version-0.55-improvingux",
      "version-0.55-timers",
      "version-0.55-debugging",
      "version-0.55-performance",
      "version-0.55-gesture-responder-system",
      "version-0.55-javascript-environment",
      "version-0.55-direct-manipulation",
      "version-0.55-colors",
      "version-0.55-integration-with-existing-apps",
      "version-0.55-building-for-tv",
      "version-0.55-running-on-device",
      "version-0.55-upgrading",
      "version-0.55-troubleshooting",
      "version-0.55-native-modules-setup"
    ],
    "Guides (iOS)": [
      "version-0.55-native-modules-ios",
      "version-0.55-native-components-ios",
      "version-0.55-linking-libraries-ios",
      "version-0.55-running-on-simulator-ios",
      "version-0.55-communication-ios",
      "version-0.55-app-extensions"
    ],
    "Guides (Android)": [
      "version-0.55-native-modules-android",
      "version-0.55-native-components-android",
      "version-0.55-headless-js-android",
      "version-0.55-signed-apk-android",
      "version-0.55-removing-default-permissions"
    ],
    "Components": [
      "version-0.55-activityindicator",
      "version-0.55-button",
      "version-0.55-datepickerios",
      "version-0.55-drawerlayoutandroid",
      "version-0.55-flatlist",
      "version-0.55-image",
      "version-0.55-imagebackground",
      "version-0.55-inputaccessoryview",
      "version-0.55-keyboardavoidingview",
      "version-0.55-listview",
      "version-0.55-maskedviewios",
      "version-0.55-modal",
      "version-0.55-navigatorios",
      "version-0.55-picker",
      "version-0.55-pickerios",
      "version-0.55-progressbarandroid",
      "version-0.55-progressviewios",
      "version-0.55-refreshcontrol",
      "version-0.55-safeareaview",
      "version-0.55-scrollview",
      "version-0.55-sectionlist",
      "version-0.55-segmentedcontrolios",
      "version-0.55-slider",
      "version-0.55-snapshotviewios",
      "version-0.55-statusbar",
      "version-0.55-switch",
      "version-0.55-tabbarios",
      "version-0.55-tabbarios-item",
      "version-0.55-text",
      "version-0.55-textinput",
      "version-0.55-toolbarandroid",
      "version-0.55-touchablehighlight",
      "version-0.55-touchablenativefeedback",
      "version-0.55-touchableopacity",
      "version-0.55-touchablewithoutfeedback",
      "version-0.55-view",
      "version-0.55-viewpagerandroid",
      "version-0.55-virtualizedlist",
      "version-0.55-webview"
    ],
    "APIs": [
      "version-0.55-accessibilityinfo",
      "version-0.55-actionsheetios",
      "version-0.55-alert",
      "version-0.55-alertios",
      "version-0.55-animated",
      "version-0.55-appregistry",
      "version-0.55-appstate",
      "version-0.55-asyncstorage",
      "version-0.55-backandroid",
      "version-0.55-backhandler",
      "version-0.55-cameraroll",
      "version-0.55-clipboard",
      "version-0.55-datepickerandroid",
      "version-0.55-dimensions",
      "version-0.55-easing",
      "version-0.55-geolocation",
      "version-0.55-imageeditor",
      "version-0.55-imagepickerios",
      "version-0.55-imagestore",
      "version-0.55-image-style-props",
      "version-0.55-interactionmanager",
      "version-0.55-keyboard",
      "version-0.55-layout-props",
      "version-0.55-layoutanimation",
      "version-0.55-linking",
      "version-0.55-listviewdatasource",
      "version-0.55-netinfo",
      "version-0.55-panresponder",
      "version-0.55-permissionsandroid",
      "version-0.55-pixelratio",
      "version-0.55-pushnotificationios",
      "version-0.55-settings",
      "version-0.55-shadow-props",
      "version-0.55-share",
      "version-0.55-statusbarios",
      "version-0.55-stylesheet",
      "version-0.55-systrace",
      "version-0.55-text-style-props",
      "version-0.55-timepickerandroid",
      "version-0.55-toastandroid",
      "version-0.55-transforms",
      "version-0.55-vibration",
      "version-0.55-vibrationios",
      "version-0.55-view-style-props"
    ]
  }
}
