{
  "docs": {
    "The Basics": [
      "getting-started",
      "tutorial",
      "props",
      "state",
      "style",
      "handling-text-input",
      "using-a-scrollview",
      "using-a-listview",
      "troubleshooting",
      "more-resources"
    ],
    "Environment setup": [
      "integration-with-existing-apps",
      "building-for-apple-tv",
      "out-of-tree-platforms"
    ],
    "Workflow": [
      "running-on-device",
      "fast-refresh",
      "debugging",
      "typescript"
    ],
    "Design": ["colors", "images", "stylesheet", "flexbox", "height-and-width"],
    "Interaction": [
      "handling-touches",
      "navigation",
      "animations",
      "gesture-responder-system"
    ],
    "Inclusion": ["accessibility"],
    "Performance": ["performance", "optimizing-flatlist-configuration"],
    "JavaScript Internals": ["javascript-environment", "timers", "hermes"],
    "Connectivity": ["network"],
    "Native Components and Modules": [
      "native-modules-setup",
      "direct-manipulation"
    ],
    "Maintaining": ["upgrading"],
    "Guides (iOS)": [
      "native-modules-ios",
      "native-components-ios",
      "linking-libraries-ios",
      "running-on-simulator-ios",
      "communication-ios",
      "app-extensions"
    ],
    "Guides (Android)": [
      "native-modules-android",
      "native-components-android",
      "headless-js-android",
      "signed-apk-android",
      "removing-default-permissions"
    ],
    "Interoperability": ["platform-specific-code"]
  },
  "api": {
    "Components": [
      "components-and-apis",
      "activityindicator",
      "button",
      "datepickerios",
      "drawerlayoutandroid",
      "flatlist",
      "image",
      "imagebackground",
      "inputaccessoryview",
      "keyboardavoidingview",
      "maskedviewios",
      "modal",
      "picker",
      "pickerios",
      "progressbarandroid",
      "progressviewios",
      "refreshcontrol",
      "safeareaview",
      "scrollview",
      "sectionlist",
      "segmentedcontrolios",
      "slider",
      "statusbar",
      "switch",
      "tabbarios",
      "tabbarios-item",
      "text",
      "textinput",
      "toolbarandroid",
      "touchablehighlight",
      "touchablenativefeedback",
      "touchableopacity",
      "touchablewithoutfeedback",
      "view",
      "viewpagerandroid",
      "virtualizedlist"
    ],
    "APIs": [
      "accessibilityinfo",
      "actionsheetios",
      "alert",
      "alertios",
      "animated",
      "appregistry",
      "appstate",
      "asyncstorage",
      "backhandler",
      "clipboard",
      "datepickerandroid",
      "dimensions",
      "easing",
      "imageeditor",
      "imagepickerios",
      "image-style-props",
      "interactionmanager",
      "keyboard",
      "layoutanimation",
      "linking",
      "panresponder",
      "permissionsandroid",
      "pixelratio",
      "pushnotificationios",
      "settings",
      "shadow-props",
      "share",
      "statusbarios",
      "systrace",
      "text-style-props",
      "timepickerandroid",
      "toastandroid",
      "transforms",
      "vibration",
      "view-style-props"
    ]
  }
}
